CHANGELOG.md
LICENSE
magicdoc/__init__.py
magicdoc/classes/GitParser.py
magicdoc/classes/Log.py
magicdoc/classes/TFMagicDoc.py
magicdoc/classes/__init__.py
magicdoc/commands/__init__.py
magicdoc/commands/tf.py
magicdoc/commands/tf_commands/__init__.py
magicdoc/commands/tf_commands/create.py
magicdoc/commands/tf_commands/show.py
magicdoc/main.py
magicdoc/modules/tree.py
magicdoc/templates/magicdoc_config.j2
magicdoc/templates/magicdoc_tf_module_config.j2
magicdoc/templates/magicdoc_tf_module_readme.j2
magicdoc-0.1.2.dist-info/entry_points.txt
magicdoc-0.1.2.dist-info/LICENSE
magicdoc-0.1.2.dist-info/WHEEL
magicdoc-0.1.2.dist-info/METADATA
magicdoc-0.1.2.dist-info/RECORD
