Metadata-Version: 2.1
Name: magicdoc
Version: 0.1.2
Summary: MagicDoc is a Python command line tool/library that is designed to provide an extremely simple way to automatically create detailed documentation for certain project types.
Home-page: https://github.com/TheCloudMage/PyPkgs-MagicDoc
License: GPL-3.0-or-later
Keywords: Packages,CloudMage,Documentation,Readme
Author: Rich Nason
Author-email: rnason@cloudmage.io
Maintainer: Rich Nason
Maintainer-email: rnason@cloudmage.io
Requires-Python: >=3.6,<4.0
Classifier: Environment :: Console
Classifier: License :: OSI Approved :: GNU General Public License v3 or later (GPLv3+)
Classifier: Operating System :: OS Independent
Classifier: Programming Language :: Python :: 3
Classifier: Programming Language :: Python :: 3.6
Classifier: Programming Language :: Python :: 3.7
Classifier: Programming Language :: Python :: 3.8
Classifier: Topic :: Software Development :: Documentation
Classifier: Topic :: Software Development :: Libraries :: Python Modules
Requires-Dist: PyYaml (>=5.3,<6.0)
Requires-Dist: click (>=7.0,<8.0)
Requires-Dist: cloudmage-jinjautils (>=1.0.2,<2.0.0)
Requires-Dist: colorama (>=0.4.3,<0.5.0)
Requires-Dist: graphviz (>=0.13.2,<0.14.0)
Requires-Dist: pyhcl (>=0.4.0,<0.5.0)
Requires-Dist: python-terraform (>=0.10.1,<0.11.0)
Requires-Dist: requests (>=2.22.0,<3.0.0)
Project-URL: Bug Tracking, https://github.com/TheCloudMage/PyPkgs-MagicDoc/issues
Project-URL: Documentation, https://github.com/TheCloudMage/PyPkgs-MagicDoc
Project-URL: Repository, https://github.com/TheCloudMage/PyPkgs-MagicDoc
Project-URL: Releases, https://github.com/TheCloudMage/PyPkgs-MagicDoc/releases
